cli/__init__.py
cli/tools.py
cli/workfrontcli.py
services/__init__.py
services/creds.py
services/db_util.py
services/settings.py
services/workfront.py
tests/test_db_connection.py
tests/test_workfront.py
workfrontutil-0.1.0.dist-info/LICENSE.md
workfrontutil-0.1.0.dist-info/METADATA
workfrontutil-0.1.0.dist-info/WHEEL
workfrontutil-0.1.0.dist-info/entry_points.txt
workfrontutil-0.1.0.dist-info/top_level.txt
workfrontutil-0.1.0.dist-info/RECORD
