Metadata-Version: 2.1
Name: workfrontutil
Version: 0.1.0
Summary: Python Wrapper for the Workfront API
Home-page: https://github.com/hjean36/workfront-util
Author: Harley Jean
Author-email: hjean35@gmail.com
License: MIT
Platform: UNKNOWN
Classifier: Programming Language :: Python :: 3
Classifier: License :: OSI Approved :: MIT License
Classifier: Operating System :: OS Independent
Requires-Python: >= 3.7
